{
    "AAAGCAACATGTCTCC-1": 4,
    "AAATGCCGTCGCCATG-1": 1,
    "AAATGCCTCTCCAGGG-1": 4,
    "AACACGTCAAGGCTCC-1": 4,
    "AACACGTGTGTGAAAT-1": 4,
    "AACCATGCACCTGGTG-1": 3,
    "AACCGCGTCGCATGAT-1": 4,
    "AACTTTCTCACTGGGC-1": 3,
    "AAGCCGCCAAGCCGCT-1": 3,
    "AAGGCAGCAAGCGAGT-1": 2,
    "AAGGTTCTCGTACGGC-1": 3,
    "ACAGCCGTCATTCACT-1": 4,
    "ACAGCTAAGACACGAC-1": 3,
    "ACATACGTCCGTTGTC-1": 4,
    "ACCGTAAAGTGGACGT-1": 4,
    "ACCGTAATCGCACTCT-1": 3,
    "ACGAGCCAGCCACCTG-1": 3,
    "ACGAGGATCGGAATCT-1": 2,
    "ACGATACAGCCAGAAC-1": 3,
    "ACGATGTTCGCCAAAT-1": 4,
    "ACGATGTTCTGAAAGA-1": 2,
    "ACGCAGCTCCATGAGT-1": 2,
    "ACGGAGACACAACTGT-1": 4,
    "ACGGGCTAGAGGTTGC-1": 1,
    "ACGGGCTAGGGCATGT-1": 4,
    "ACTATCTAGATATACG-1": 4,
    "ACTGAACAGTCATCCA-1": 1,
    "ACTGAGTGTACGACCC-1": 4,
    "ACTGCTCGTTGCGCAC-1": 3,
    "ACTTGTTGTGTGACCC-1": 4,
    "ACTTGTTTCATTCACT-1": 3,
    "ACTTTCACAGTTCATG-1": 4,
    "ACTTTCATCCTGCTTG-1": 1,
    "ACTTTCATCGCCTGTT-1": 4,
    "AGAGCTTGTAGCGCAA-1": 3,
    "AGATTGCCATACTCTT-1": 1,
    "AGCAGCCTCTCAACTT-1": 1,
    "AGCATACTCGCAAACT-1": 4,
    "AGGCCACCATCTGGTA-1": 4,
    "AGGTCCGCACGGATAG-1": 3,
    "AGTCTTTCACATTTCT-1": 2,
    "AGTCTTTCATCATCCC-1": 3,
    "AGTGGGATCACCTCGT-1": 4,
    "ATAACGCAGAGCTGCA-1": 4,
    "ATAACGCAGAGCTTCT-1": 2,
    "ATCACGAGTCTCCACT-1": 4,
    "ATCGAGTCATTCTCAT-1": 3,
    "ATCTACTAGGCTCATT-1": 4,
    "ATGCGATAGACGCTTT-1": 4,
    "ATGCGATTCAGAGCTT-1": 4,
    "ATGTGTGTCGCTTAGA-1": 4,
    "ATTACTCAGCGCTCCA-1": 3,
    "ATTACTCTCCACTCCA-1": 2,
    "CAACCAATCTCTGTCG-1": 1,
    "CAACCTCAGGCTAGCA-1": 4,
    "CAACCTCCACACCGCA-1": 2,
    "CAAGAAAGTGCACTTA-1": 2,
    "CAAGTTGGTCCTAGCG-1": 4,
    "CACACAAGTAGCGCTC-1": 2,
    "CACACTCCAGGTCCAC-1": 1,
    "CACATAGCAACACCCG-1": 4,
    "CACATAGTCTCGCTTG-1": 4,
    "CACATTTGTGTTAAGA-1": 4,
    "CACCACTTCGTACCGG-1": 1,
    "CAGAGAGTCCAAACTG-1": 3,
    "CAGCAGCCAAGCCCAC-1": 1,
    "CAGGTGCGTCATCGGC-1": 3,
    "CAGGTGCTCATGGTCA-1": 3,
    "CAGTCCTCACGCCAGT-1": 1,
    "CATATGGGTTGTCTTT-1": 1,
    "CATCAAGCAGACTCGC-1": 3,
    "CATCAGATCACCACCT-1": 4,
    "CATGGCGAGACAATAC-1": 3,
    "CATTATCCACCGAATT-1": 1,
    "CCAATCCTCCCATTAT-1": 3,
    "CCACCTATCATGGTCA-1": 3,
    "CCATGTCAGTTAACGA-1": 4,
    "CCATTCGAGCGTGAAC-1": 4,
    "CCCAATCTCACTTACT-1": 4,
    "CCTACCACACCGTTGG-1": 3,
    "CCTAGCTAGGGCATGT-1": 3,
    "CCTCAGTCAATAACGA-1": 4,
    "CCTCAGTCACGTCAGC-1": 4,
    "CCTCAGTGTCAGATAA-1": 4,
    "CCTCTGATCATAAAGG-1": 1,
    "CCTTTCTCATTGGTAC-1": 3,
    "CGACTTCAGTCACGCC-1": 4,
    "CGAGCCAGTAGCTGCC-1": 3,
    "CGATTGAAGCTAGCCC-1": 4,
    "CGCTATCAGTGGCACA-1": 3,
    "CGCTTCACATCCCATC-1": 4,
    "CGCTTCATCTATCGCC-1": 3,
    "CGGAGTCCACGCCAGT-1": 1,
    "CGGCTAGCACCCATTC-1": 4,
    "CGGTTAATCCTTTCTC-1": 3,
    "CGTGTAATCATAAAGG-1": 4,
    "CTAACTTCAAGAAAGG-1": 4,
    "CTAAGACTCGGCATCG-1": 4,
    "CTACATTAGGGCTTCC-1": 4,
    "CTACGTCTCTTACCGC-1": 4,
    "CTCACACCAAACGTGG-1": 4,
    "CTCACACCACAACGCC-1": 1,
    "CTCGTACTCTACCTGC-1": 2,
    "CTCGTCACACCTATCC-1": 4,
    "CTCTGGTCAGTAACGG-1": 4,
    "CTGATAGAGCCACGCT-1": 2,
    "CTGATCCCACGACGAA-1": 3,
    "CTGCTGTAGATCTGCT-1": 2,
    "CTGGTCTTCTGGTTCC-1": 3,
    "CTTACCGTCCAAATGC-1": 4,
    "CTTGGCTAGAAACGCC-1": 2,
    "CTTGGCTTCTTACCTA-1": 2,
    "GAAATGATCACGACTA-1": 3,
    "GAACATCAGTGATCGG-1": 1,
    "GAACCTACAGGAATGC-1": 4,
    "GACACGCCATTGGGCC-1": 2,
    "GACCTGGGTTGAACTC-1": 3,
    "GACCTGGTCTCTAAGG-1": 3,
    "GACGCGTAGCAGCGTA-1": 3,
    "GACTACATCCCATTAT-1": 4,
    "GAGTCCGAGAGTGACC-1": 1,
    "GATCGATGTGGGTATG-1": 4,
    "GATCGCGAGAAGGGTA-1": 3,
    "GATCGTATCGGCTACG-1": 4,
    "GATCGTATCGTTACAG-1": 2,
    "GATGAGGAGTGAAGAG-1": 4,
    "GATGCTATCTGGCGTG-1": 1,
    "GATTCAGCAGTGGGAT-1": 1,
    "GATTCAGCATTTGCTT-1": 4,
    "GCAGTTAAGCCAGGAT-1": 4,
    "GCAGTTACAATGGATA-1": 3,
    "GCATGATAGGGTCTCC-1": 4,
    "GCATGCGAGCGTGAGT-1": 2,
    "GCCTCTAAGTGTACGG-1": 3,
    "GCGCAACCAAACTGTC-1": 3,
    "GCGCAGTTCCATGAAC-1": 4,
    "GCGCCAACACCTTGTC-1": 3,
    "GCGCGATCAAGCCGTC-1": 3,
    "GCTGCAGAGACCCACC-1": 3,
    "GCTGGGTAGACTTGAA-1": 3,
    "GCTGGGTTCCGCTGTT-1": 2,
    "GGAAAGCGTGCAGACA-1": 1,
    "GGAATAACAGTGACAG-1": 4,
    "GGACGTCAGCTCAACT-1": 1,
    "GGATTACTCTTGTTTG-1": 2,
    "GGCAATTCATGCTAGT-1": 4,
    "GGGCACTTCTGGAGCC-1": 3,
    "GGGTCTGGTCTCCATC-1": 4,
    "GGTGCGTTCAAACAAG-1": 2,
    "GGTGTTAGTTTCCACC-1": 1,
    "GGTGTTATCAGGCGAA-1": 4,
    "GTAACTGTCTAACTTC-1": 4,
    "GTATCTTAGACTGTAA-1": 4,
    "GTATCTTGTACCGTTA-1": 4,
    "GTCACAATCATAACCG-1": 4,
    "GTCGTAAGTCTTCTCG-1": 2,
    "GTGCAGCAGCACGCCT-1": 4,
    "GTGCATACATACTCTT-1": 4,
    "GTGCATATCGAGAGCA-1": 4,
    "GTGTGCGCAATGTTGC-1": 3,
    "GTTAAGCTCATCATTC-1": 2,
    "GTTACAGTCTGACCTC-1": 4,
    "GTTCTCGAGCGTAATA-1": 3,
    "GTTCTCGTCCCATTTA-1": 1,
    "GTTTCTATCACTATTC-1": 4,
    "TACGGATTCATTGCCC-1": 3,
    "TACTCGCTCGGCGCTA-1": 2,
    "TAGCCGGAGCCGATTT-1": 4,
    "TAGGCATGTCCGTGAC-1": 3,
    "TATCTCACAGGTTTCA-1": 4,
    "TATTACCTCAATCACG-1": 3,
    "TCAATCTGTAGAGGAA-1": 1,
    "TCAGATGGTGCACTTA-1": 1,
    "TCCACACGTAAGGGAA-1": 3,
    "TCGAGGCGTGTCAATC-1": 4,
    "TCTCATAGTACTCTCC-1": 4,
    "TCTCTAAAGCGTTCCG-1": 3,
    "TCTTCGGCACATCTTT-1": 4,
    "TCTTTCCCATGGTTGT-1": 3,
    "TGAAAGATCATGCATG-1": 2,
    "TGATTTCTCCACGAAT-1": 4,
    "TGCACCTCATAAGACA-1": 3,
    "TGGACGCAGATCTGCT-1": 1,
    "TGGACGCAGGATATAC-1": 3,
    "TGGCCAGTCAGAGACG-1": 4,
    "TGGCCAGTCGGAATCT-1": 4,
    "TGGCGCAGTCTCTCTG-1": 4,
    "TGTCCCATCAACGCTA-1": 1,
    "TGTGTTTCAGGTCCAC-1": 2,
    "TTAACTCCACCGGAAA-1": 2,
    "TTAGGACTCACGCGGT-1": 4,
    "TTAGGACTCGACGGAA-1": 1,
    "TTAGGCATCTGCTGCT-1": 1,
    "TTCTCAACACCGGAAA-1": 4,
    "TTCTCAACAGACGCTC-1": 4,
    "TTGACTTTCCGCAAGC-1": 3,
    "TTTACTGAGCCAGGAT-1": 2,
    "TTTCCTCAGTAGGTGC-1": 4,
    "TTTGGTTGTTCGTTGA-1": 4,
    "TTTGTCAGTGAGGGTT-1": 2
}