{
  "AACTCCCAGTGTCCCG-1": 2,
  "AACTTTCCACACCGCA-1": 3,
  "AACTTTCTCTTGCCGT-1": 2,
  "AAGGAGCTCGCCTGTT-1": 2,
  "AAGGCAGCATGAACCT-1": 1,
  "AAGGTTCGTGACGCCT-1": 1,
  "AAGGTTCTCTGTTGAG-1": 2,
  "ACACCAACACTGTGTA-1": 3,
  "ACAGCTATCTGGCGTG-1": 3,
  "ACATCAGAGTGTACCT-1": 2,
  "ACATCAGTCTTGTATC-1": 3,
  "ACATGGTAGCTGTTCA-1": 2,
  "ACATGGTCATTATCTC-1": 3,
  "ACCCACTAGATATGCA-1": 1,
  "ACCCACTAGATCACGG-1": 3,
  "ACCCACTTCAAACGGG-1": 2,
  "ACGATACCACCATCCT-1": 2,
  "ACGATACGTTGGAGGT-1": 3,
  "ACGGCCATCTTGCAAG-1": 2,
  "ACGGGCTCAGCTGCTG-1": 2,
  "ACTGCTCCAGCCTTGG-1": 3,
  "ACTGCTCGTACTTCTT-1": 2,
  "ACTGTCCTCACCATAG-1": 3,
  "ACTTGTTTCAGCTTAG-1": 2,
  "AGACGTTTCTCGGACG-1": 3,
  "AGAGTGGGTTCCTCCA-1": 2,
  "AGCAGCCCAAAGCAAT-1": 2,
  "AGCATACGTTAAGTAG-1": 2,
  "AGCGTATGTGAAATCA-1": 2,
  "AGCTCTCTCAAAGACA-1": 3,
  "AGGGAGTTCGTCCGTT-1": 3,
  "AGGGTGATCGAACGGA-1": 2,
  "AGGTCATCATTACGAC-1": 2,
  "AGTGAGGCAATCCAAC-1": 2,
  "AGTTGGTAGCCACTAT-1": 2,
  "ATAGACCCATTTCAGG-1": 2,
  "ATCATGGTCAACACCA-1": 2,
  "ATCTGCCAGGATATAC-1": 3,
  "ATGAGGGGTGCAACGA-1": 2,
  "ATTACTCAGATGGGTC-1": 3,
  "ATTACTCGTCTCAACA-1": 3,
  "CAACCAACAGTACACT-1": 3,
  "CAAGAAAAGCAGCCTC-1": 2,
  "CAAGGCCCATCCTTGC-1": 2,
  "CACACCTGTCTAGCGC-1": 2,
  "CACAGGCAGGGTTTCT-1": 3,
  "CACAGTAAGATCCGAG-1": 2,
  "CACATAGTCAATACCG-1": 3,
  "CAGAATCAGATATACG-1": 1,
  "CAGCATAGTCAGATAA-1": 1,
  "CAGCTAACACGGTGTC-1": 3,
  "CAGCTGGAGTCGAGTG-1": 3,
  "CATATGGTCCTGCTTG-1": 3,
  "CATATTCAGGTACTCT-1": 2,
  "CCAATCCGTTTACTCT-1": 1,
  "CCAATCCTCCACGCAG-1": 3,
  "CCACCTACATCCGTGG-1": 3,
  "CCACCTAGTACTCAAC-1": 2,
  "CCACGGAGTGCCTGGT-1": 1,
  "CCATGTCAGATGGCGT-1": 3,
  "CCATGTCAGCACGCCT-1": 2,
  "CCCTCCTCATAACCTG-1": 3,
  "CCGTGGAGTCAACATC-1": 2,
  "CCGTTCAGTTGCCTCT-1": 3,
  "CCTACACCATGGTTGT-1": 3,
  "CCTACACTCTCGGACG-1": 2,
  "CCTCAGTAGCGTTTAC-1": 1,
  "CCTTACGAGCGTGAAC-1": 2,
  "CCTTCCCAGGCAGTCA-1": 3,
  "CGACCTTTCCTAAGTG-1": 3,
  "CGACCTTTCTTCTGGC-1": 3,
  "CGATCGGGTCGCGGTT-1": 3,
  "CGCCAAGTCCGCAAGC-1": 3,
  "CGCTGGAGTCCGTTAA-1": 3,
  "CGCTTCAGTTTAGGAA-1": 1,
  "CGGACACTCACTTCAT-1": 3,
  "CGGACACTCGGCTACG-1": 2,
  "CGGACTGCAGTAGAGC-1": 3,
  "CGTAGCGGTTGGACCC-1": 3,
  "CGTCAGGCACCGAAAG-1": 2,
  "CGTCCATAGACAATAC-1": 3,
  "CGTCCATAGCTATGCT-1": 3,
  "CGTGTCTTCTGTTTGT-1": 2,
  "CGTTCTGCAAAGGAAG-1": 1,
  "CGTTCTGTCGCATGAT-1": 2,
  "CGTTGGGTCGTTGCCT-1": 2,
  "CTAAGACGTTCATGGT-1": 3,
  "CTACACCGTCTCGTTC-1": 3,
  "CTACATTAGGGCTTCC-1": 2,
  "CTACCCAAGCAGGTCA-1": 3,
  "CTCACACCAAAGGCGT-1": 2,
  "CTCACACTCCCTCTTT-1": 2,
  "CTCATTATCAGTACGT-1": 2,
  "CTCATTATCCTGCCAT-1": 2,
  "CTCGAGGGTCAGAAGC-1": 2,
  "CTCGTCACAAATTGCC-1": 2,
  "CTCTAATGTCATGCAT-1": 3,
  "CTGAAGTCAGCAGTTT-1": 2,
  "CTGATCCAGCAATCTC-1": 3,
  "CTGCGGACAAGCTGGA-1": 2,
  "CTGCGGACATCTACGA-1": 2,
  "CTGCTGTGTATAGTAG-1": 2,
  "CTGTTTATCCTTGCCA-1": 2,
  "CTTAACTCAGGGCATA-1": 2,
  "CTTAGGAGTCACCTAA-1": 2,
  "GAAACTCCACGTGAGA-1": 2,
  "GACCTGGGTTGAACTC-1": 3,
  "GACGGCTCAGCTGCAC-1": 2,
  "GACGTGCCATCTACGA-1": 2,
  "GACTAACCAATAACGA-1": 2,
  "GACTAACCAATGGACG-1": 2,
  "GAGTCCGAGAGTGACC-1": 1,
  "GATCGCGAGAAGGGTA-1": 1,
  "GATGAGGTCTACCAGA-1": 3,
  "GCAATCAGTCGAGATG-1": 2,
  "GCACTCTCAGCGTTCG-1": 3,
  "GCAGTTACAATGGATA-1": 3,
  "GCAGTTATCGCAGGCT-1": 2,
  "GCATACAAGCGATCCC-1": 2,
  "GCATACAGTCGCATAT-1": 3,
  "GCGCAGTTCCATTCTA-1": 3,
  "GCGCGATCATTTGCTT-1": 2,
  "GCGCGATGTAGCGCAA-1": 3,
  "GGAAAGCCACGAGGTA-1": 2,
  "GGAACTTGTATCAGTC-1": 2,
  "GGAACTTGTTATGCGT-1": 2,
  "GGACAAGGTCTCTTAT-1": 3,
  "GGACAGATCGTGACAT-1": 2,
  "GGATGTTGTGCCTTGG-1": 3,
  "GGATTACTCTTGTTTG-1": 2,
  "GGCTCGACAGTGGGAT-1": 2,
  "GGCTCGACATTTCAGG-1": 3,
  "GGGACCTTCATCATTC-1": 2,
  "GGGACCTTCTCCGGTT-1": 1,
  "GGTATTGCATTGAGCT-1": 2,
  "GGTGTTAAGACAGACC-1": 3,
  "GTAACTGCATAGGATA-1": 2,
  "GTACTTTCATTGTGCA-1": 2,
  "GTACTTTGTGCAACTT-1": 2,
  "GTACTTTTCTCCTATA-1": 3,
  "GTATCTTCATGAGCGA-1": 2,
  "GTCAAGTTCATAACCG-1": 3,
  "GTCAAGTTCCTATTCA-1": 3,
  "GTCACGGGTAGTACCT-1": 2,
  "GTCATTTGTGCAGACA-1": 2,
  "GTCTTCGGTGCCTGGT-1": 1,
  "GTGCAGCAGGACACCA-1": 2,
  "GTGCAGCAGGTACTCT-1": 2,
  "GTGCATAGTTGTGGCC-1": 3,
  "GTGGGTCTCTGTTTGT-1": 2,
  "GTGTGCGTCCGCGCAA-1": 2,
  "GTTAAGCAGAAACGCC-1": 2,
  "TAAGAGACACTAGTAC-1": 3,
  "TACGGATAGAACAACT-1": 2,
  "TACGGTAGTTTAGCTG-1": 2,
  "TACTCGCAGGCCGAAT-1": 3,
  "TAGAGCTCATGATCCA-1": 2,
  "TAGCCGGAGCCGATTT-1": 2,
  "TAGTGGTCAGCTCCGA-1": 2,
  "TATCAGGTCGACCAGC-1": 2,
  "TATCTCAGTTAAAGTG-1": 2,
  "TATTACCGTACGACCC-1": 3,
  "TATTACCTCACCCGAG-1": 3,
  "TCAACGACACAAGCCC-1": 2,
  "TCAATCTCATGGTCTA-1": 3,
  "TCAATCTTCCTGTAGA-1": 1,
  "TCAGCTCTCGCTTGTC-1": 3,
  "TCAGGTAAGAGGTACC-1": 2,
  "TCAGGTAAGTTCCACA-1": 1,
  "TCATTACTCTTGTACT-1": 1,
  "TCATTTGCATCACAAC-1": 1,
  "TCCACACCAGTCGTGC-1": 3,
  "TCCACACGTCAGAGGT-1": 2,
  "TCGTACCGTCCGCTGA-1": 2,
  "TCGTAGAAGAAACCAT-1": 1,
  "TCGTAGAGTCTTGCGG-1": 2,
  "TCGTAGATCATGCAAC-1": 2,
  "TCTATTGGTTTAGCTG-1": 2,
  "TGAGAGGCATCCGCGA-1": 3,
  "TGAGCATGTTTGGCGC-1": 2,
  "TGCCCATCATTACCTT-1": 3,
  "TGCCCATTCCGTCAAA-1": 2,
  "TGCCCTATCCGCATCT-1": 3,
  "TGCGCAGCACTTAACG-1": 3,
  "TGGACGCAGTTTGCGT-1": 3,
  "TGGCCAGTCTAACTGG-1": 2,
  "TGGCGCACACACCGCA-1": 1,
  "TGGTTAGAGAATGTTG-1": 2,
  "TGGTTAGGTCCAACTA-1": 2,
  "TGTATTCAGTATGACA-1": 3,
  "TGTCCCAGTGTGACCC-1": 3,
  "TTAGGCATCTCTGAGA-1": 3,
  "TTAGTTCGTCGAACAG-1": 1,
  "TTCGAAGCACCGGAAA-1": 2,
  "TTGAACGAGATCTGCT-1": 3,
  "TTGAACGTCCGCGGTA-1": 2,
  "TTGCGTCTCTTACCTA-1": 1,
  "TTGGAACTCCTCGCAT-1": 3,
  "TTTGCGCGTAGCGTAG-1": 3,
  "TTTGCGCTCTATCCCG-1": 2
}
