{
  "AAAGCAACACGGCTAC-1": 2,
  "AAATGCCAGATATACG-1": 3,
  "AAATGCCAGCGCTCCA-1": 3,
  "AACACGTGTGAGGGTT-1": 3,
  "AACACGTGTGGCGAAT-1": 1,
  "AACACGTGTTAGAACA-1": 3,
  "AACCGCGAGAATTCCC-1": 3,
  "AACTCTTTCGTTTATC-1": 3,
  "AAGCCGCGTGCACCAC-1": 3,
  "ACATACGAGGCTCAGA-1": 3,
  "ACCAGTATCAGCTCGG-1": 3,
  "ACGAGCCAGTTAGCGG-1": 1,
  "ACGAGCCTCGATCCCT-1": 3,
  "ACGCCAGGTGAAAGAG-1": 3,
  "ACGGAGACACAACTGT-1": 3,
  "ACTGATGGTGCCTGCA-1": 1,
  "ACTGCTCCAAGCCGTC-1": 3,
  "ACTTTCACACCATCCT-1": 3,
  "AGAATAGCATTAGCCA-1": 1,
  "AGATTGCCAGCTTCGG-1": 1,
  "AGCAGCCTCTCAACTT-1": 2,
  "AGCCTAACAATGGACG-1": 3,
  "AGGCCACGTGCGATAG-1": 3,
  "AGGCCGTTCTGTCCGT-1": 1,
  "AGGGATGAGTCATCCA-1": 3,
  "AGGGATGTCCTATTCA-1": 1,
  "AGGTCCGTCCACTGGG-1": 3,
  "AGTCTTTGTAGCGTAG-1": 3,
  "AGTGGGATCACCTCGT-1": 3,
  "ATAGACCCAGGAATGC-1": 3,
  "ATAGACCCATTTCAGG-1": 3,
  "ATAGACCTCCAAGCCG-1": 3,
  "ATCATCTAGCACCGTC-1": 3,
  "ATCATCTAGTGTACTC-1": 1,
  "ATCATCTTCGCATGAT-1": 3,
  "ATGAGGGTCAGCAACT-1": 3,
  "ATGCGATGTTGATTCG-1": 3,
  "ATTGGTGCAAGACACG-1": 2,
  "ATTGGTGCAGCTGTGC-1": 3,
  "CAACCAAAGCAAATCA-1": 1,
  "CAACCAACAAGTAGTA-1": 2,
  "CAAGATCTCTACTTAC-1": 3,
  "CAAGGCCAGGCAAAGA-1": 1,
  "CACACCTAGCTTCGCG-1": 1,
  "CACAGGCGTGCAACTT-1": 3,
  "CACATAGGTACCGGCT-1": 3,
  "CACATAGGTCCTGCTT-1": 3,
  "CACATAGTCTCGCTTG-1": 3,
  "CACCAGGAGACAAAGG-1": 3,
  "CACTCCAAGACCCACC-1": 1,
  "CAGAATCAGGCAGTCA-1": 3,
  "CAGCAGCGTTCCACAA-1": 1,
  "CAGCCGAAGGACAGAA-1": 1,
  "CAGCGACTCAATACCG-1": 3,
  "CAGGTGCCATCGACGC-1": 1,
  "CAGTCCTTCGTCTGCT-1": 3,
  "CAGTCCTTCTAAGCCA-1": 1,
  "CATCAAGCAAACGTGG-1": 3,
  "CATCAAGTCCCATTTA-1": 3,
  "CATCCACAGTCTTGCA-1": 2,
  "CATGCCTAGAAACCTA-1": 1,
  "CATTCGCCAGTTAACC-1": 1,
  "CCAATCCCACCTCGTT-1": 3,
  "CCACCTAGTAAATGTG-1": 3,
  "CCACTACAGAGGTACC-1": 3,
  "CCAGCGAAGAAACCGC-1": 1,
  "CCAGCGAGTATCTGCA-1": 3,
  "CCATTCGCAATGGAGC-1": 1,
  "CCCTCCTCATAACCTG-1": 1,
  "CCGTACTCAGCATGAG-1": 2,
  "CCGTTCATCGCATGGC-1": 1,
  "CCTAAAGAGGATCGCA-1": 3,
  "CCTACCAGTGACCAAG-1": 3,
  "CCTTACGAGCTAGTCT-1": 3,
  "CGAGAAGAGTGAACAT-1": 3,
  "CGAGCACCACTCTGTC-1": 1,
  "CGAGCACCAGGATCGA-1": 3,
  "CGAGCCAGTAGCTGCC-1": 1,
  "CGATCGGGTGGGTCAA-1": 3,
  "CGATGTATCTCAAACG-1": 2,
  "CGCTGGACACATTTCT-1": 3,
  "CGCTTCAGTGTCCTCT-1": 3,
  "CGCTTCATCTGTGCAA-1": 3,
  "CGGACACTCACTTCAT-1": 3,
  "CGGAGTCCACGAAACG-1": 3,
  "CGGAGTCCACGCCAGT-1": 2,
  "CGGGTCAAGATCTGAA-1": 3,
  "CGTTAGAAGCGCTCCA-1": 3,
  "CGTTCTGAGAGAACAG-1": 1,
  "CTACACCAGGACCACA-1": 1,
  "CTACATTAGTGAACAT-1": 1,
  "CTAGTGAAGCGCTTAT-1": 3,
  "CTCACACTCAACACGT-1": 3,
  "CTCAGAACAAGGCTCC-1": 1,
  "CTCATTAAGCTACCTA-1": 2,
  "CTCCTAGTCTGTCTCG-1": 1,
  "CTCGGGAAGTTAGCGG-1": 3,
  "CTCGTCAAGTATTGGA-1": 3,
  "CTCTACGGTAGCCTCG-1": 3,
  "CTGAAGTAGGAGTTGC-1": 3,
  "CTTACCGTCCAAATGC-1": 3,
  "CTTAGGAGTTACTGAC-1": 2,
  "GACACGCAGTACTTGC-1": 3,
  "GACCAATAGTTAGGTA-1": 3,
  "GACCTGGCAAGAGGCT-1": 3,
  "GACCTGGCAGGGTTAG-1": 3,
  "GACTAACCATGTAAGA-1": 3,
  "GATCGATCACGAAACG-1": 3,
  "GATCGTATCTGTTGAG-1": 3,
  "GATCTAGTCGCGTAGC-1": 1,
  "GCAATCAGTCGAGATG-1": 3,
  "GCACATAGTCAAACTC-1": 1,
  "GCACTCTCAGCGTTCG-1": 1,
  "GCATACAAGCGATCCC-1": 1,
  "GCATGATAGGGTCTCC-1": 3,
  "GCATGCGAGAAACCGC-1": 1,
  "GCATGCGCATATGGTC-1": 3,
  "GCATGTACAGTTAACC-1": 1,
  "GCATGTATCACTCCTG-1": 1,
  "GCCAAATTCTGCGACG-1": 3,
  "GCCTCTACAGAAGCAC-1": 3,
  "GCGCAACAGACAAAGG-1": 1,
  "GCGCAGTAGGTTCCTA-1": 3,
  "GCTGCAGAGACCCACC-1": 1,
  "GCTGCTTTCTAACCGA-1": 3,
  "GCTGGGTAGACTTGAA-1": 1,
  "GCTGGGTCACCTTGTC-1": 3,
  "GCTTCCAGTGACTACT-1": 2,
  "GGAAAGCCATAGACTC-1": 1,
  "GGAACTTGTAGAGTGC-1": 3,
  "GGAATAACAACTGCTA-1": 3,
  "GGACAGATCACAGTAC-1": 1,
  "GGATTACGTAAGTTCC-1": 3,
  "GGCCGATAGCTGCCCA-1": 3,
  "GGGCATCCATGTTCCC-1": 3,
  "GGTGTTAAGCTGAAAT-1": 3,
  "GTACTCCAGCTGGAAC-1": 1,
  "GTAGGCCCAAGCGATG-1": 3,
  "GTCATTTCAAGGTTTC-1": 1,
  "GTCATTTGTTGTACAC-1": 3,
  "GTCCTCACAACGCACC-1": 1,
  "GTCCTCACAGCCTATA-1": 3,
  "GTCCTCAGTGAGCGAT-1": 2,
  "GTCGGGTAGAGACTAT-1": 1,
  "GTCGTAATCTCGGACG-1": 3,
  "GTCGTAATCTCTTATG-1": 3,
  "GTCTCGTGTCAGAATA-1": 1,
  "GTGCATAAGAGGTACC-1": 3,
  "GTGTGCGGTGTGACCC-1": 2,
  "GTTAAGCAGAGACGAA-1": 3,
  "GTTAAGCAGCGTGTCC-1": 3,
  "TAAACCGCAATCCAAC-1": 3,
  "TAAGTGCTCGCACTCT-1": 1,
  "TACAGTGGTTCATGGT-1": 3,
  "TACCTTAGTGTGGTTT-1": 3,
  "TACCTTATCTGATACG-1": 3,
  "TACGGTATCGCATGAT-1": 1,
  "TACTTGTAGAGTCGGT-1": 3,
  "TAGAGCTAGAGCTTCT-1": 1,
  "TAGCCGGTCACTTATC-1": 3,
  "TATCAGGAGACACGAC-1": 3,
  "TATCAGGGTAGGAGTC-1": 3,
  "TATGCCCGTTCCCTTG-1": 3,
  "TCAACGAAGCGTTCCG-1": 3,
  "TCAGATGGTCTCTTTA-1": 3,
  "TCAGATGTCACCGGGT-1": 3,
  "TCAGGTACAATGGAGC-1": 1,
  "TCATTTGAGTTAAGTG-1": 3,
  "TCGTACCGTGCTAGCC-1": 3,
  "TCTATTGCATTGAGCT-1": 3,
  "TCTCATAGTACTCTCC-1": 3,
  "TCTCTAATCAGTGCAT-1": 2,
  "TCTTCGGGTGCACCAC-1": 1,
  "TGAAAGATCATCACCC-1": 3,
  "TGACGGCGTTGTCGCG-1": 3,
  "TGACTTTGTGTGACGA-1": 3,
  "TGAGCCGCAACTGCTA-1": 1,
  "TGCCCTATCGTTTGCC-1": 3,
  "TGCGCAGTCACAACGT-1": 3,
  "TGCGGGTAGCTACCTA-1": 3,
  "TGGACGCTCCTCAACC-1": 2,
  "TGGCGCACACACCGCA-1": 2,
  "TGGCGCACACACGCTG-1": 3,
  "TGGCGCAGTATTCGTG-1": 1,
  "TGGTTAGCACAGCCCA-1": 3,
  "TGGTTAGCAGCATACT-1": 1,
  "TGGTTCCCAGCGATCC-1": 3,
  "TGTCCCAAGTCGTACT-1": 2,
  "TGTTCCGTCGAATCCA-1": 3,
  "TTAGTTCCAGCTGTTA-1": 3,
  "TTAGTTCTCGCCATAA-1": 3,
  "TTCCCAGCAAGTCTAC-1": 1,
  "TTCCCAGCAATACGCT-1": 3,
  "TTCTACAAGCCTATGT-1": 1,
  "TTCTTAGAGTACGCCC-1": 3,
  "TTGACTTGTCATACTG-1": 1,
  "TTGCGTCCACAGATTC-1": 1,
  "TTGGCAATCGAATCCA-1": 3,
  "TTTGCGCGTAGCGTAG-1": 1,
  "TTTGCGCGTGCTGTAT-1": 3
}
