{
  "AAACCTGCACTGTGTA-1": 1,
  "AAAGCAACATGTCTCC-1": 3,
  "AAAGCAATCCTCATTA-1": 3,
  "AACACGTAGGATGTAT-1": 2,
  "AACGTTGCAAACAACA-1": 1,
  "AACTGGTTCTCGCATC-1": 3,
  "AAGACCTAGACAGGCT-1": 2,
  "AAGCCGCGTGACCAAG-1": 3,
  "AAGGCAGCAAACCCAT-1": 3,
  "AATCCAGCAGCCAATT-1": 3,
  "ACACCGGTCCACGAAT-1": 3,
  "ACACTGAGTATCGCAT-1": 3,
  "ACCAGTATCAGCTCGG-1": 2,
  "ACCCACTTCACTCTTA-1": 3,
  "ACGATACTCTCGGACG-1": 2,
  "ACGCAGCGTTCCGTCT-1": 2,
  "ACGCCAGAGATGGGTC-1": 2,
  "ACGGCCAGTATAGGGC-1": 3,
  "ACGGCCATCAACGCTA-1": 3,
  "ACGGGCTGTAGCGATG-1": 3,
  "ACGGGTCTCAATCACG-1": 1,
  "ACTATCTGTGTTGGGA-1": 3,
  "ACTGAACAGATGCCTT-1": 3,
  "ACTGCTCCAGCCTTGG-1": 3,
  "ACTGTCCAGATACACA-1": 3,
  "ACTTACTAGTACGTAA-1": 3,
  "ACTTGTTCATCACAAC-1": 1,
  "ACTTGTTCATCCCACT-1": 3,
  "AGAATAGGTAAGTTCC-1": 3,
  "AGATTGCAGGGAAACA-1": 3,
  "AGCTCTCCACCAGGCT-1": 3,
  "AGCTCTCGTAAGTTCC-1": 3,
  "AGCTTGAAGTGCTGCC-1": 1,
  "AGGTCATCATCTCCCA-1": 3,
  "AGGTCATGTCAGAGGT-1": 2,
  "AGGTCCGTCCACTGGG-1": 2,
  "AGTGGGAAGCAACGGT-1": 3,
  "ATAGACCAGCACCGTC-1": 3,
  "ATCATCTAGCTTCGCG-1": 3,
  "ATCATCTTCGGGAGTA-1": 2,
  "ATCCGAAGTTTGACAC-1": 3,
  "ATGTGTGCATGCGCAC-1": 3,
  "ATTACTCTCGGGAGTA-1": 3,
  "ATTCTACAGTTAGCGG-1": 2,
  "ATTGGACTCAACACGT-1": 3,
  "CAACCAACAAAGCGGT-1": 3,
  "CAACCAACAAGTAGTA-1": 1,
  "CAAGATCGTCCGAGTC-1": 2,
  "CAAGATCTCTACTTAC-1": 3,
  "CAAGTTGAGATCTGCT-1": 3,
  "CAAGTTGAGCGTGAGT-1": 2,
  "CACACTCAGACCACGA-1": 3,
  "CACACTCAGACGCTTT-1": 1,
  "CACATTTAGTGACATA-1": 3,
  "CACCACTTCCGCAGTG-1": 3,
  "CACCAGGGTAGCGTGA-1": 2,
  "CAGAATCAGGGAAACA-1": 3,
  "CAGCATATCTTAGCCC-1": 2,
  "CAGCCGAGTACGACCC-1": 3,
  "CAGCTGGCACAGGTTT-1": 3,
  "CAGTCCTTCGAGAACG-1": 3,
  "CAGTCCTTCGTCTGCT-1": 3,
  "CATCAAGAGTCTCCTC-1": 3,
  "CATCAGAGTCGCATAT-1": 3,
  "CATCGAAGTTCGTGAT-1": 3,
  "CATCGGGAGCCATCGC-1": 3,
  "CATTCGCGTGACCAAG-1": 2,
  "CCAATCCCACAGCCCA-1": 3,
  "CCATGTCAGTTAACGA-1": 3,
  "CCATTCGCAAACTGTC-1": 1,
  "CCATTCGGTCCCTTGT-1": 3,
  "CCCTCCTTCCGAGCCA-1": 2,
  "CCGTGGATCCGTAGGC-1": 2,
  "CCGTTCAGTTAAGAAC-1": 1,
  "CCTACACAGCGTGAAC-1": 3,
  "CCTACACTCGTTACAG-1": 2,
  "CCTACCAAGGCTCTTA-1": 2,
  "CCTTACGCAGTGGAGT-1": 3,
  "CCTTTCTAGACGCTTT-1": 2,
  "CGAACATTCTGATTCT-1": 2,
  "CGATGGCAGAGTACCG-1": 3,
  "CGATGTAGTACAAGTA-1": 3,
  "CGCTATCCACCCATTC-1": 3,
  "CGCTTCACAGCGTTCG-1": 3,
  "CGGACGTAGAGTACAT-1": 1,
  "CGGACGTTCGCCTGTT-1": 2,
  "CGGCTAGTCCGCGGTA-1": 3,
  "CGTCTACCAGTCAGAG-1": 1,
  "CGTGAGCCACGGCGTT-1": 2,
  "CTACACCAGACGCACA-1": 3,
  "CTACATTCATATACGC-1": 3,
  "CTACATTTCTGTCTAT-1": 2,
  "CTAGAGTGTTGCGCAC-1": 2,
  "CTAGCCTTCTACTCAT-1": 3,
  "CTCATTATCAGTACGT-1": 3,
  "CTCCTAGTCAGTTTGG-1": 1,
  "CTCGAAAAGTTCGCAT-1": 3,
  "CTCGAAAGTCGACTGC-1": 1,
  "CTCGAGGGTTTAGCTG-1": 2,
  "CTCGGGACAAGTACCT-1": 3,
  "CTCGTACTCACTCTTA-1": 1,
  "CTCTAATAGACTACAA-1": 3,
  "CTCTGGTAGACTTTCG-1": 3,
  "CTGCTGTAGCCTATGT-1": 2,
  "CTGTGCTTCCTGCCAT-1": 2,
  "CTTACCGCACCTCGTT-1": 1,
  "CTTCTCTGTAAATACG-1": 2,
  "CTTTGCGCAGCCTATA-1": 2,
  "GAACCTATCGCCGTGA-1": 3,
  "GACACGCCATTGGGCC-1": 2,
  "GACACGCTCTTCCTTC-1": 2,
  "GACCAATCATCGGGTC-1": 3,
  "GACGCGTAGCCAGAAC-1": 3,
  "GACGGCTGTCTCTCTG-1": 2,
  "GACGTGCCACCAACCG-1": 3,
  "GACTAACTCAGTGTTG-1": 3,
  "GACTGCGGTCCGACGT-1": 2,
  "GAGGTGATCGTATCAG-1": 3,
  "GATCGATAGCGTTCCG-1": 3,
  "GATCGTATCGTTACAG-1": 3,
  "GATGAGGCAATGGACG-1": 3,
  "GATTCAGCATGTTCCC-1": 2,
  "GCAAACTAGGGTCGAT-1": 2,
  "GCAATCACAGTCCTTC-1": 2,
  "GCATGATTCCGCATAA-1": 3,
  "GCGACCAAGACTAGGC-1": 3,
  "GCGCAACAGACAAAGG-1": 2,
  "GCTGCGACACGCGAAA-1": 3,
  "GCTGCGACAGATGGGT-1": 1,
  "GGAAAGCAGGTGCACA-1": 3,
  "GGAAAGCCAGGGATTG-1": 3,
  "GGAATAATCATGCAAC-1": 1,
  "GGACGTCAGCTCAACT-1": 1,
  "GGATGTTCACAGAGGT-1": 2,
  "GGGACCTCAGACGCAA-1": 1,
  "GGGATGAGTGCGATAG-1": 3,
  "GTACTCCAGCTGGAAC-1": 2,
  "GTACTTTGTGCAACGA-1": 2,
  "GTACTTTTCTCCTATA-1": 2,
  "GTAGTCAAGGGCTTCC-1": 3,
  "GTATTCTAGATAGCAT-1": 1,
  "GTATTCTCATTCACTT-1": 3,
  "GTCAAGTAGGCCCTTG-1": 2,
  "GTCAAGTGTGTGGTTT-1": 2,
  "GTCACGGTCATCACCC-1": 3,
  "GTCATTTGTACCATCA-1": 3,
  "GTCGGGTCATGCCTAA-1": 3,
  "GTCGGGTTCCACGTTC-1": 3,
  "GTGCAGCAGGACACCA-1": 3,
  "GTGCGGTGTAATAGCA-1": 2,
  "GTGTGCGGTGTGACCC-1": 1,
  "GTTACAGAGCCATCGC-1": 3,
  "GTTACAGGTACCGAGA-1": 3,
  "GTTCATTCAGCGATCC-1": 3,
  "GTTTCTAGTAAACACA-1": 3,
  "TACGGATAGAACAACT-1": 3,
  "TACTCGCGTATCTGCA-1": 3,
  "TACTTGTGTCGCGTGT-1": 1,
  "TAGACCATCACCCTCA-1": 2,
  "TAGCCGGAGCACACAG-1": 3,
  "TAGGCATGTAGCTGCC-1": 3,
  "TATGCCCGTCTCCACT-1": 2,
  "TCAACGAAGAAACCAT-1": 2,
  "TCAATCTGTACCGTTA-1": 1,
  "TCACAAGTCTACTTAC-1": 3,
  "TCAGATGGTCTCTTTA-1": 3,
  "TCAGCTCAGGGAAACA-1": 3,
  "TCCACACTCCTCATTA-1": 2,
  "TCGCGAGCATCACCCT-1": 2,
  "TCGGTAACAAAGAATC-1": 3,
  "TCTCATAGTCCTCTTG-1": 3,
  "TCTCTAAGTGAACCTT-1": 1,
  "TCTTCGGGTTCGCGAC-1": 3,
  "TCTTTCCCATCGGGTC-1": 2,
  "TGACAACAGACTAGAT-1": 3,
  "TGACAACTCGCAGGCT-1": 3,
  "TGACTAGAGCGATGAC-1": 3,
  "TGAGCCGAGATGTCGG-1": 3,
  "TGCCCATCATTACCTT-1": 2,
  "TGCGGGTCAACTGCTA-1": 3,
  "TGCGTGGTCTACCAGA-1": 3,
  "TGCTACCAGGCCCTCA-1": 3,
  "TGCTACCGTTCGGCAC-1": 1,
  "TGGACGCGTGTTTGGT-1": 2,
  "TGGACGCTCCTCAACC-1": 1,
  "TGGCTGGAGCTCCTCT-1": 2,
  "TGGGAAGCAACAACCT-1": 1,
  "TGGGAAGGTAGGACAC-1": 3,
  "TGGTTCCCACTACAGT-1": 2,
  "TGTCCCACACCAGGTC-1": 3,
  "TGTCCCATCAACGCTA-1": 1,
  "TGTGGTACAGGACCCT-1": 1,
  "TGTGTTTTCAGCTCGG-1": 1,
  "TTAACTCAGGCATGGT-1": 3,
  "TTAGGACAGGAGTTGC-1": 3,
  "TTATGCTGTATAATGG-1": 3,
  "TTCGAAGTCTTTACGT-1": 3,
  "TTGTAGGCACCTCGGA-1": 3,
  "TTTATGCAGCAATCTC-1": 3,
  "TTTCCTCTCAACACAC-1": 2
}
