{
  "AAACCTGTCGGATGTT-1": 1,
  "AAACGGGTCACAGTAC-1": 3,
  "AAACGGGTCCTCTAGC-1": 3,
  "AAAGTAGAGCGCCTTG-1": 1,
  "AACTCAGTCGAGGTAG-1": 3,
  "AACTGGTAGGATCGCA-1": 1,
  "AACTGGTCACTTAAGC-1": 1,
  "AACTTTCCACCTATCC-1": 1,
  "AACTTTCGTAGGGTAC-1": 3,
  "AAGCCGCCATGGGACA-1": 3,
  "AAGCCGCTCCCAAGAT-1": 3,
  "AAGTCTGGTGACTACT-1": 3,
  "AATCCAGGTACCGAGA-1": 1,
  "AATCCAGGTCCGTCAG-1": 1,
  "AATCGGTAGAACAATC-1": 2,
  "ACAGCTACAGGGAGAG-1": 2,
  "ACATACGGTAATCGTC-1": 3,
  "ACATACGGTGTTTGTG-1": 1,
  "ACCAGTAAGGGCTTGA-1": 1,
  "ACCTTTAAGCTAAACA-1": 2,
  "ACGAGCCAGCCACCTG-1": 3,
  "ACGAGGATCAACACCA-1": 3,
  "ACGATGTTCGAATGCT-1": 1,
  "ACGCCAGGTAGGGACT-1": 3,
  "ACGCCAGGTTCCAACA-1": 1,
  "ACGGGTCCAGTCGTGC-1": 1,
  "ACGTCAAAGGATATAC-1": 1,
  "ACTTTCACAGTCAGCC-1": 1,
  "AGAGCGATCTACTCAT-1": 3,
  "AGATCTGAGCCGATTT-1": 3,
  "AGATTGCAGCCAGGAT-1": 3,
  "AGGCCGTTCTGTCCGT-1": 3,
  "AGGTCATTCCGCTGTT-1": 3,
  "AGGTCCGCATCGATTG-1": 3,
  "AGTAGTCCAGGAATCG-1": 3,
  "AGTCTTTCAATGAAAC-1": 3,
  "ATCATCTTCATAAAGG-1": 3,
  "ATCCGAAGTAGCGTAG-1": 1,
  "ATCGAGTAGACGCACA-1": 1,
  "ATCTGCCCACGGTAAG-1": 3,
  "ATGAGGGGTGCAACGA-1": 3,
  "ATTATCCAGACCTAGG-1": 3,
  "ATTGGACTCGGCGCAT-1": 3,
  "ATTGGTGTCCGGGTGT-1": 1,
  "ATTTCTGCATGGTAGG-1": 2,
  "CAACCTCCACACCGCA-1": 1,
  "CAAGATCCAGTACACT-1": 1,
  "CACACCTCAGGGTATG-1": 3,
  "CACACCTGTCATATGC-1": 1,
  "CACATAGAGAAACCGC-1": 2,
  "CACCACTTCAGTTGAC-1": 3,
  "CACCAGGTCCACTGGG-1": 3,
  "CAGCAGCTCGACAGCC-1": 3,
  "CAGCATATCTGGTTCC-1": 1,
  "CAGTAACTCTTAGCCC-1": 3,
  "CAGTCCTGTCGTGGCT-1": 3,
  "CATCGAAAGTGGGATC-1": 3,
  "CCAATCCCATCTCGCT-1": 1,
  "CCATTCGCAAACTGTC-1": 2,
  "CCCAGTTTCTGTCTAT-1": 3,
  "CCCTCCTTCCGAGCCA-1": 3,
  "CCGTTCACATGTTCCC-1": 3,
  "CCGTTCAGTTAAGAAC-1": 2,
  "CCTAAAGCACGTCAGC-1": 3,
  "CCTACACAGATAGCAT-1": 3,
  "CCTACACCATGGTTGT-1": 3,
  "CCTAGCTCACCGCTAG-1": 1,
  "CGAACATGTAGCGTAG-1": 1,
  "CGAACATGTGTGAAAT-1": 1,
  "CGACCTTCATATACGC-1": 3,
  "CGAGAAGGTCCGTTAA-1": 3,
  "CGAGCACCAGGCTGAA-1": 3,
  "CGCCAAGCAAGAGTCG-1": 1,
  "CGCGGTACACTAGTAC-1": 3,
  "CGCTATCAGGTGTGGT-1": 1,
  "CGCTGGACAGCCTGTG-1": 1,
  "CGCTTCAAGCGTCTAT-1": 1,
  "CGGGTCACAAGTTCTG-1": 1,
  "CGGGTCATCTAACCGA-1": 3,
  "CGTCACTAGACGACGT-1": 1,
  "CGTCAGGCAGGAATCG-1": 1,
  "CGTCCATAGCGGCTTC-1": 1,
  "CGTCTACAGCGTAATA-1": 3,
  "CGTGAGCAGAATGTTG-1": 1,
  "CGTGAGCCACGGCGTT-1": 3,
  "CGTTAGACAGGGATTG-1": 1,
  "CGTTCTGGTAGAGCTG-1": 1,
  "CTAACTTAGACACTAA-1": 1,
  "CTAAGACGTGTCCTCT-1": 1,
  "CTAATGGTCAACACCA-1": 1,
  "CTACATTGTAGCAAAT-1": 2,
  "CTCACACCACGCATCG-1": 3,
  "CTCACACGTCGACTAT-1": 3,
  "CTCATTAAGCAGCCTC-1": 1,
  "CTCATTAAGTGCTGCC-1": 3,
  "CTCATTATCTTCATGT-1": 1,
  "CTCCTAGAGACCTTTG-1": 1,
  "CTCGTACCAAAGTCAA-1": 1,
  "CTCGTCATCAGCCTAA-1": 3,
  "CTCTAATAGGCCCGTT-1": 3,
  "CTGAAACTCGGTTCGG-1": 1,
  "CTGATAGGTAAAGTCA-1": 1,
  "CTGATCCCAATGGTCT-1": 1,
  "CTGATCCCAGACGCAA-1": 1,
  "CTTAACTTCCATGCTC-1": 1,
  "CTTACCGCACTATCTT-1": 1,
  "CTTAGGAGTATGAAAC-1": 1,
  "CTTGGCTAGCGATTCT-1": 3,
  "CTTGGCTAGTACACCT-1": 3,
  "CTTGGCTCATGCAATC-1": 3,
  "CTTTGCGAGGCATGTG-1": 3,
  "GAACCTAGTTCGTTGA-1": 3,
  "GAACCTATCGGAGCAA-1": 1,
  "GAACCTATCTCTGTCG-1": 1,
  "GAATGAAGTCCAAGTT-1": 2,
  "GACACGCTCTTCCTTC-1": 3,
  "GACAGAGAGTCGTACT-1": 1,
  "GACCTGGGTTGAACTC-1": 3,
  "GACGTTAAGATCCTGT-1": 1,
  "GACGTTAAGTTGCAGG-1": 1,
  "GACTGCGTCCGAGCCA-1": 3,
  "GATCGATAGGGCATGT-1": 1,
  "GATCGTAGTCCGAAGA-1": 1,
  "GATGCTATCTTCGAGA-1": 1,
  "GATTCAGTCTATCCCG-1": 1,
  "GCAATCAGTCTAGCGC-1": 2,
  "GCATGTAGTATCTGCA-1": 1,
  "GCCAAATGTTGCGCAC-1": 1,
  "GCGCAACAGACAAAGG-1": 3,
  "GCGCAACGTGCGAAAC-1": 3,
  "GCGCAACTCAAAGACA-1": 2,
  "GCTCCTAAGATCCCAT-1": 3,
  "GGAATAACAACTGCTA-1": 3,
  "GGACAAGTCTTGCAAG-1": 2,
  "GGATGTTGTTTCCACC-1": 3,
  "GGCAATTCATGCTAGT-1": 1,
  "GGCTGGTCATCTCCCA-1": 3,
  "GGGACCTAGTACGCGA-1": 1,
  "GGTATTGAGTTGTCGT-1": 1,
  "GGTGAAGCACCCATTC-1": 1,
  "GGTGTTAAGCTGAAAT-1": 1,
  "GTAACGTTCAGCGACC-1": 2,
  "GTAACTGCACGCCAGT-1": 3,
  "GTACGTATCATTATCC-1": 3,
  "GTACTCCCAGACGCTC-1": 3,
  "GTATCTTAGGGCTTCC-1": 1,
  "GTCAAGTTCCTATTCA-1": 3,
  "GTCACGGTCATATCGG-1": 1,
  "GTCCTCAGTGAGCGAT-1": 2,
  "GTGCATAGTTGGAGGT-1": 1,
  "GTGGGTCTCGACAGCC-1": 1,
  "GTGTGCGAGCTGAAAT-1": 1,
  "GTTAAGCTCGGTCTAA-1": 3,
  "GTTACAGAGGAGTAGA-1": 2,
  "GTTACAGTCTGTTGAG-1": 2,
  "GTTCATTTCCCTAATT-1": 3,
  "TAAGAGACATGGAATA-1": 3,
  "TAAGCGTGTTCATGGT-1": 3,
  "TACACGATCACTTCAT-1": 3,
  "TACCTTAAGAGACTTA-1": 3,
  "TAGACCAGTTACGCGC-1": 2,
  "TAGTGGTGTGCTTCTC-1": 1,
  "TAGTTGGCACGAGAGT-1": 1,
  "TATCAGGGTCGAATCT-1": 3,
  "TATCTCAAGACCGGAT-1": 1,
  "TCACGAAAGTAACCCT-1": 3,
  "TCACGAACAAACAACA-1": 1,
  "TCCACACGTGCACTTA-1": 3,
  "TCGAGGCAGCTGCGAA-1": 3,
  "TCGCGTTGTACATGTC-1": 2,
  "TCGCGTTTCGGAAACG-1": 3,
  "TCGGGACAGAGCTATA-1": 2,
  "TCGTAGATCCACGCAG-1": 3,
  "TCTTTCCAGGACATTA-1": 1,
  "TGACAACTCGGCTTGG-1": 1,
  "TGACGGCAGCCCGAAA-1": 1,
  "TGACGGCGTTGTCGCG-1": 1,
  "TGAGGGATCGTTTATC-1": 2,
  "TGATTTCGTACTCGCG-1": 3,
  "TGCCCTACAGAAGCAC-1": 1,
  "TGCTGCTAGAGTACCG-1": 1,
  "TGCTGCTTCGGAGCAA-1": 2,
  "TGGACGCTCTTAGCCC-1": 2,
  "TGGCCAGCACCAACCG-1": 1,
  "TGGCTGGCAGCTCGAC-1": 1,
  "TGGCTGGTCTTGCATT-1": 2,
  "TGGGAAGTCAACGAAA-1": 1,
  "TGGGCGTCATACGCCG-1": 1,
  "TGTGTTTGTCTCCATC-1": 1,
  "TTATGCTAGCTGTTCA-1": 1,
  "TTATGCTTCATCGCTC-1": 1,
  "TTCGAAGCACTGTCGG-1": 2,
  "TTGAACGCAAAGAATC-1": 3,
  "TTGCCGTCAACGATCT-1": 3,
  "TTGCCGTTCCAGAGGA-1": 1,
  "TTGCGTCTCAAGGCTT-1": 1,
  "TTGTAGGCAATAGAGT-1": 2,
  "TTTCCTCCAGCGTAAG-1": 1,
  "TTTGGTTCATGGGAAC-1": 1,
  "TTTGTCAGTGTTCGAT-1": 3
}
